cupcake/__init__.py
cupcake/breadcrumbs/__init__.py
cupcake/breadcrumbs/pathview.py
cupcake/config/__init__.py
cupcake/config/dark.toml
cupcake/config/light.toml
cupcake/config/stipple.xbm
cupcake/config/styles.py
cupcake/diffeditor/__init__.py
cupcake/diffeditor/differ.py
cupcake/diffeditor/pane.py
cupcake/editor.py
cupcake/imageviewer/__init__.py
cupcake/languages.py
cupcake/texteditor/__init__.py
cupcake/texteditor/autocomplete/__init__.py
cupcake/texteditor/autocomplete/item.py
cupcake/texteditor/autocomplete/kind.py
cupcake/texteditor/autocomplete/kinds.py
cupcake/texteditor/highlighter.py
cupcake/texteditor/linenumbers/__init__.py
cupcake/texteditor/linenumbers/breakpoint.py
cupcake/texteditor/minimap.py
cupcake/texteditor/syntax.py
cupcake/texteditor/text.py
cupcake/utils/__init__.py
cupcake/utils/canvas.py
cupcake/utils/directorytree.py
cupcake/utils/filetype.py
cupcake/utils/frame.py
cupcake/utils/label.py
cupcake/utils/menubutton.py
cupcake/utils/scrollableframe.py
cupcake/utils/scrollbar.py
cupcake/utils/text.py
cupcake/utils/toplevel.py
cupcake/utils/tree.py
cupcake_editor-0.25.8.dist-info/LICENSE
cupcake_editor-0.25.8.dist-info/METADATA
cupcake_editor-0.25.8.dist-info/WHEEL
cupcake_editor-0.25.8.dist-info/RECORD
