Metadata-Version: 2.1
Name: cupcake-editor
Version: 0.25.8
Summary: Embeddable text editor with autocompletions
License: MIT
Author: Billy
Author-email: billydevbusiness@gmail.com
Requires-Python: >=3.10,<4.0
Classifier: License :: OSI Approved :: MIT License
Classifier: Operating System :: OS Independent
Classifier: Programming Language :: Python :: 3
Classifier: Programming Language :: Python :: 3.10
Classifier: Programming Language :: Python :: 3.11
Classifier: Programming Language :: Python :: 3
